gova_commons/__init__.py
gova_commons/enums.py
gova_commons/events.py
gova_commons/logger.py
gova_commons/models.py
gova_commons/settings.py
gova_commons/lib/models.py
gova_commons/lib/base/actions.py
gova_commons/lib/discord/actions.py
gova_commons/lib/discord/config.py
gova_commons/lib/discord/context.py
gova_commons/utils/kafka.py
gova_commons/utils/utils.py
gova_commons/utils/db/__init__.py
gova_commons/utils/db/session_manager.py
gova_commons/utils/db/utils.py
gova_commons-2.2.2.dist-info/METADATA
gova_commons-2.2.2.dist-info/WHEEL
gova_commons-2.2.2.dist-info/RECORD
