Metadata-Version: 2.4
Name: gova-commons
Version: 2.2.2
Summary: Common backend utilities
Project-URL: Repository, https://github.com/Gova-Chat/commons
Requires-Python: >=3.13
Requires-Dist: aiohttp>=3.13.2
Requires-Dist: pydantic>=2.12.4
Requires-Dist: sqlalchemy>=2.0.44
